journaltop/__init__.py
journaltop/client.py
journaltop/data/__init__.py
journaltop/data/config.py
journaltop/errors/__init__.py
journaltop/errors/base.py
journaltop/errors/journal_exceptions.py
journaltop/log/__init__.py
journaltop/log/logger.py
journaltop/models/__init__.py
journaltop/models/homework.py
journaltop/models/schedule.py
journaltop/models/user_info.py
journaltop/tests/integration/test_client.py
journaltop/tests/integration/test_transport.py
journaltop/tests/unit/test_app_key_parser.py
journaltop/tests/unit/test_exception.py
journaltop/tests/unit/test_logger.py
journaltop/transport.py
journaltop/utils/__init__.py
journaltop/utils/app_key.py
journaltop-0.1.0.dist-info/WHEEL
journaltop-0.1.0.dist-info/METADATA
journaltop-0.1.0.dist-info/RECORD
