Metadata-Version: 2.3
Name: journaltop
Version: 0.1.0
Summary: Async-friendly SDK for ittopjournal API
Author: trapplus
Author-email: trapplus <blazer19092008@gmail.com>
License: MIT
Requires-Dist: beautifulsoup4>=4.14.2
Requires-Dist: httpx>=0.28.1
Requires-Dist: pydantic>=2.12.3
Requires-Python: >=3.13
